torchaudio_augmentations/__init__.py
torchaudio_augmentations/apply.py
torchaudio_augmentations/compose.py
torchaudio_augmentations/utils.py
torchaudio_augmentations/augmentations/__init__.py
torchaudio_augmentations/augmentations/delay.py
torchaudio_augmentations/augmentations/filter.py
torchaudio_augmentations/augmentations/gain.py
torchaudio_augmentations/augmentations/high_low_pass.py
torchaudio_augmentations/augmentations/noise.py
torchaudio_augmentations/augmentations/pitch_shift.py
torchaudio_augmentations/augmentations/polarity_inversion.py
torchaudio_augmentations/augmentations/random_resized_crop.py
torchaudio_augmentations/augmentations/reverb.py
torchaudio_augmentations/augmentations/reverse.py
torchaudio_augmentations-0.2.4.dist-info/LICENSE
torchaudio_augmentations-0.2.4.dist-info/METADATA
torchaudio_augmentations-0.2.4.dist-info/WHEEL
torchaudio_augmentations-0.2.4.dist-info/top_level.txt
torchaudio_augmentations-0.2.4.dist-info/RECORD
