Metadata-Version: 2.1
Name: torchaudio-augmentations
Version: 0.2.4
Summary: Audio augmentations library for PyTorch, for audio in the time-domain.
Home-page: https://github.com/spijkervet/torchaudio-augmentations
Author: Janne Spijkervet
Author-email: janne.spijkervet@gmail.com
License: MIT
Platform: UNKNOWN
Classifier: License :: OSI Approved :: MIT License
Classifier: Programming Language :: Python
Classifier: Programming Language :: Python :: 3
Classifier: Programming Language :: Python :: 3.6
Classifier: Programming Language :: Python :: Implementation :: CPython
Classifier: Programming Language :: Python :: Implementation :: PyPy
Requires-Python: >=3.6.0
License-File: LICENSE
Requires-Dist: numpy
Requires-Dist: torch
Requires-Dist: torchaudio
Requires-Dist: julius
Requires-Dist: wavaugment
Requires-Dist: torch-pitch-shift
Provides-Extra: fancy_feature
Provides-Extra: test
Requires-Dist: pytest ; extra == 'test'
Requires-Dist: pytest-cov ; extra == 'test'
Requires-Dist: black ; extra == 'test'
Requires-Dist: librosa ; extra == 'test'
